ludi/__init__.py
ludi/assets.py
ludi/ludi.py
ludi/cli/__init__.py
ludi/cli/analyze.py
ludi/cli/config.py
ludi/cli/main.py
ludi/decompilers/__init__.py
ludi/decompilers/angr/__init__.py
ludi/decompilers/angr/config.py
ludi/decompilers/angr/decompiler.py
ludi/decompilers/angr/managers.py
ludi/decompilers/base/__init__.py
ludi/decompilers/base/config.py
ludi/decompilers/base/decompiler.py
ludi/decompilers/base/managers.py
ludi/decompilers/base/query.py
ludi/decompilers/base/types.py
ludi/decompilers/ghidra/__init__.py
ludi/decompilers/ghidra/config.py
ludi/decompilers/ghidra/decompiler.py
ludi/decompilers/ghidra/managers.py
ludi/decompilers/ida/__init__.py
ludi/decompilers/ida/config.py
ludi/decompilers/ida/decompiler.py
ludi/decompilers/ida/managers.py
ludi-0.0.1.dist-info/licenses/LICENSE
ludi-0.0.1.dist-info/METADATA
ludi-0.0.1.dist-info/WHEEL
ludi-0.0.1.dist-info/entry_points.txt
ludi-0.0.1.dist-info/top_level.txt
ludi-0.0.1.dist-info/RECORD
