Metadata-Version: 2.4
Name: ludi
Version: 0.0.1
Summary: Ludi Unifies Decompiler Interfaces
Author-email: Han Dai <pypi@han.do>
License: MIT License
Project-URL: homepage, https://github.com/DennyDai/LUDI
Project-URL: documentation, https://github.com/DennyDai/LUDI
Project-URL: repository, https://github.com/DennyDai/LUDI
Requires-Python: >=3
License-File: LICENSE
Requires-Dist: headless-ida
Requires-Dist: angr
Requires-Dist: pyhidra
Requires-Dist: pyyaml
Dynamic: license-file
